glyphoji/__init__.py
glyphoji/data/data.json
glyphoji/glyphoji.py
glyphoji-0.3.1.dist-info/LICENSE
glyphoji-0.3.1.dist-info/METADATA
glyphoji-0.3.1.dist-info/WHEEL
glyphoji-0.3.1.dist-info/RECORD
