Metadata-Version: 2.1
Name: glyphoji
Version: 0.3.1
Summary: Modern hieroglyphs in the terminal.
Home-page: https://pypi.org/project/glyphoji
License: MIT
Author: Richard Mwewa
Author-email: rly0nheart@duck.com
Requires-Python: >=3.7,<4.0
Classifier: Development Status :: 5 - Production/Stable
Classifier: Environment :: Console
Classifier: Intended Audience :: Developers
Classifier: License :: OSI Approved :: MIT License
Classifier: Natural Language :: English
Classifier: Operating System :: OS Independent
Classifier: Programming Language :: Python :: 3
Classifier: Programming Language :: Python :: 3.7
Classifier: Programming Language :: Python :: 3.8
Classifier: Programming Language :: Python :: 3.9
Classifier: Programming Language :: Python :: 3.10
Classifier: Programming Language :: Python :: 3.11
Classifier: Topic :: Artistic Software
Project-URL: Repository, https://github.com/rly0nheart/glyphoji
